django_saml2_auth/__init__.py
django_saml2_auth/urls.py
django_saml2_auth/views.py
django_saml2_auth/templates/django_saml2_auth/denied.html
django_saml2_auth/templates/django_saml2_auth/signout.html
django_saml2_auth_ai-2.1.6.dist-info/LICENSE
django_saml2_auth_ai-2.1.6.dist-info/METADATA
django_saml2_auth_ai-2.1.6.dist-info/WHEEL
django_saml2_auth_ai-2.1.6.dist-info/top_level.txt
django_saml2_auth_ai-2.1.6.dist-info/RECORD
